{"id":"2194605","game":"L Ogaard vs R Hoen","result":"1-0","moveCount":44,"year":1973,"event":"Oslo CI","eco":"A04 Reti Opening","pgn":"[Event \"Oslo CI\"]\n[Site \"Oslo\"]\n[Date \"1973.04.17\"]\n[EventDate \"?\"]\n[Round \"5\"]\n[Result \"1-0\"]\n[White \"Leif Ogaard\"]\n[Black \"Ragnar Hoen\"]\n[ECO \"A04\"]\n[WhiteElo \"2340\"]\n[BlackElo \"2300\"]\n[PlyCount \"88\"]\n\n1. Nf3 c5 2. c4 Nc6 3. Nc3 g6 4. e3 Bg7 5. d4 cxd4 6. exd4 d6 7. h3 Nf6 8. d5 Nb8 9. Be3 O-O 10. Be2 e5 11. dxe6 Bxe6 12. Nd4 Nc6 13. Nxe6 fxe6 14. O-O d5 15. Bg5 d4 16. Ne4 Qb6 17. Bxf6 Bxf6 18. Rb1 Be7 19. b4 Rad8 20. Bd3 Qc7 21. c5 Ne5 22. Qe2 Rf4 23. Nd2 Kg7 24. Rfe1 Nxd3 25. Qxd3 e5 26. Re2 Bf6 27. Ne4 Be7 28. Rc2 Qc6 29. f3 a6 30. a3 Rd7 31. Re2 Rf7 32. Nd2 Rf5 33. Nc4 Qe6 34. Rbe1 Bf6 35. Re4 h5 36. f4 Qc6 37. fxe5 Bg5 38. e6 Re7 39. Qxd4+ Bf6 40. Qd3 Qb5 41. Qd2 Qc6 42. Qd6 Qa4 43. Ne3 Rg5 44. h4 1-0","Event":"Oslo CI","Site":"Oslo","Date":"1973.04.17","EventDate":"?","Round":"5","Result":"1-0","White":"Leif Ogaard","Black":"Ragnar Hoen","ECO":"A04","WhiteElo":"2340","BlackElo":"2300","PlyCount":"88","moves":["Nf3","c5","c4","Nc6","Nc3","g6","e3","Bg7","d4","cxd4","exd4","d6","h3","Nf6","d5","Nb8","Be3","O-O","Be2","e5","dxe6","Bxe6","Nd4","Nc6","Nxe6","fxe6","O-O","d5","Bg5","d4","Ne4","Qb6","Bxf6","Bxf6","Rb1","Be7","b4","Rad8","Bd3","Qc7","c5","Ne5","Qe2","Rf4","Nd2","Kg7","Rfe1","Nxd3","Qxd3","e5","Re2","Bf6","Ne4","Be7","Rc2","Qc6","f3","a6","a3","Rd7","Re2","Rf7","Nd2","Rf5","Nc4","Qe6","Rbe1","Bf6","Re4","h5","f4","Qc6","fxe5","Bg5","e6","Re7","Qxd4+","Bf6","Qd3","Qb5","Qd2","Qc6","Qd6","Qa4","Ne3","Rg5","h4"],"fen":"8/1p2r1k1/p2QPbp1/2P3rp/qP2R2P/P3N3/6P1/4R1K1 b - - 0 44"}