{"id":"1381346","game":"V Osnos vs A Rutman","result":"1-0","moveCount":52,"year":1997,"event":"Ozery op1 Seniors","eco":"E69 King's Indian, Fianchetto, Classical Main line","pgn":"[Event \"Ozery op1 Seniors\"]\n[Site \"Ozery\"]\n[Date \"1997.??.??\"]\n[EventDate \"?\"]\n[Round \"9\"]\n[Result \"1-0\"]\n[White \"Viacheslav Osnos\"]\n[Black \"Aleksandr Rutman\"]\n[ECO \"E69\"]\n[WhiteElo \"?\"]\n[BlackElo \"?\"]\n[PlyCount \"103\"]\n\n1.c4 Nf6 2.Nf3 g6 3.d4 Bg7 4.g3 d6 5.Bg2 O-O 6.O-O Nbd7 7.Nc3 e5 8.e4 c6 9.h3 Qb6 10.c5 dxc5 11.dxe5 Ne8 12.e6 fxe6 13.Ng5 Ne5 14.f4 c4+ 15.Kh2 Nd3 16.e5 Nc7 17.b3 Qd4 18.Bd2 Nd5 19.Ne2 Qc5 20.Ne4 Qa3 21.bxc4 Nb6 22.Qb3 Qxb3 23.axb3 Nd7 24.Nd4 N7c5 25.Nxc5 Nxc5 26.Bb4 b6 27.Bxc6 Rb8 28.Rxa7 Bxe5 29.Nf3 Bf6 30.Nd2 Rf7 31.Rxf7 Kxf7 32.Ne4 Be7 33.Ng5+ Bxg5 34.fxg5+ Kg8 35.Bc3 Bb7 36.Be5 Ra8 37.Bxb7 Nxb7 38.b4 Ra2+ 39.Kg1 Nd8 40.Ra1 Rxa1+ 41.Bxa1 Nc6 42.Bc3 Kf7 43.b5 Nb8 44.c5 bxc5 45.b6 Ke7 46.Be5 Na6 47.b7 Kd7 48.b8=Q Nxb8 49.Bxb8 Kc6 50.Kf2 Kd5 51.Ke3 e5 52.Bc7 1-0","Event":"Ozery op1 Seniors","Site":"Ozery","Date":"1997.??.??","EventDate":"1997.??.??","Round":"9","Result":"1-0","White":"Viacheslav Osnos","Black":"Aleksandr Rutman","ECO":"E69","WhiteElo":"?","BlackElo":"?","PlyCount":"103","moves":["c4","Nf6","Nf3","g6","d4","Bg7","g3","d6","Bg2","O-O","O-O","Nbd7","Nc3","e5","e4","c6","h3","Qb6","c5","dxc5","dxe5","Ne8","e6","fxe6","Ng5","Ne5","f4","c4+","Kh2","Nd3","e5","Nc7","b3","Qd4","Bd2","Nd5","Ne2","Qc5","Ne4","Qa3","bxc4","Nb6","Qb3","Qxb3","axb3","Nd7","Nd4","N7c5","Nxc5","Nxc5","Bb4","b6","Bxc6","Rb8","Rxa7","Bxe5","Nf3","Bf6","Nd2","Rf7","Rxf7","Kxf7","Ne4","Be7","Ng5+","Bxg5","fxg5+","Kg8","Bc3","Bb7","Be5","Ra8","Bxb7","Nxb7","b4","Ra2+","Kg1","Nd8","Ra1","Rxa1+","Bxa1","Nc6","Bc3","Kf7","b5","Nb8","c5","bxc5","b6","Ke7","Be5","Na6","b7","Kd7","b8=Q","Nxb8","Bxb8","Kc6","Kf2","Kd5","Ke3","e5","Bc7"],"fen":"8/2B4p/6p1/2pkp1P1/8/4K1PP/8/8 b - - 1 52","Year":"1997"}