{"id":"2522027","game":"F Baragar vs Z Vranesic","result":"½-½","moveCount":30,"year":1981,"event":"Canadian Championship","eco":"E59 Nimzo-Indian, 4.e3, Main line","pgn":"[Event \"CAN-ch / Zonal\"]\n[Site \"Montreal CAN\"]\n[Date \"1981.05.??\"]\n[EventDate \"1981.05.16\"]\n[Round \"?\"]\n[Result \"1/2-1/2\"]\n[White \"Fletcher Baragar\"]\n[Black \"Zvonko Vranesic\"]\n[ECO \"E59\"]\n[WhiteElo \"2270\"]\n[BlackElo \"2390\"]\n[PlyCount \"60\"]\n\n1. d4 Nf6 2. c4 e6 3. Nc3 Bb4 4. e3 O-O 5. Bd3 d5 6. Nf3 c5 7. O-O Nc6 8. a3 Bxc3 9. bxc3 dxc4 10. Bxc4 Qc7 11. Ba2 Rd8 12. Qe2 h6 13. Bb2 e5 14. dxe5 Nxe5 15. Nxe5 Qxe5 16. c4 Qe7 17. Rad1 Bf5 18. f3 Rxd1 19. Rxd1 Rd8 20. Rxd8+ Qxd8 21. Bc3 Qd3 22. Qxd3 Bxd3 23. Bxf6 gxf6 24. Kf2 f5 25. Ke1 Kg7 26. Kd2 Bf1 27. g3 Kf6 28. Ke1 Bd3 29. Kd2 Bf1 30. Ke1 1/2-1/2","Event":"CAN-ch / Zonal","Site":"Montreal CAN","Date":"1981.05.??","EventDate":"1981.05.??","Round":"?","Result":"1/2-1/2","White":"Fletcher Baragar","Black":"Zvonko Vranesic","ECO":"E59","WhiteElo":"2270","BlackElo":"2390","PlyCount":"60","moves":["d4","Nf6","c4","e6","Nc3","Bb4","e3","O-O","Bd3","d5","Nf3","c5","O-O","Nc6","a3","Bxc3","bxc3","dxc4","Bxc4","Qc7","Ba2","Rd8","Qe2","h6","Bb2","e5","dxe5","Nxe5","Nxe5","Qxe5","c4","Qe7","Rad1","Bf5","f3","Rxd1","Rxd1","Rd8","Rxd8+","Qxd8","Bc3","Qd3","Qxd3","Bxd3","Bxf6","gxf6","Kf2","f5","Ke1","Kg7","Kd2","Bf1","g3","Kf6","Ke1","Bd3","Kd2","Bf1","Ke1"],"fen":"8/pp3p2/5k1p/2p2p2/2P5/P3PPP1/B6P/4Kb2 b - - 6 30","Year":"1981"}