{"id":"1497384","game":"R Griffiths vs J Loughran","result":"1-0","moveCount":38,"year":2008,"event":"Irish Championship","eco":"C45 Scotch Game","pgn":"[Event \"Irish Championship\"]\n[Site \"Dublin IRL\"]\n[Date \"2008.07.12\"]\n[EventDate \"?\"]\n[Round \"8\"]\n[Result \"1-0\"]\n[White \"Ryan Rhys Griffiths\"]\n[Black \"John Loughran\"]\n[ECO \"C45\"]\n[WhiteElo \"?\"]\n[BlackElo \"1789\"]\n[PlyCount \"76\"]\n\n1. e4 e5 2. Nf3 Nc6 3. d4 exd4 4. Nxd4 Bc5 5. Nxc6 Qf6 6. Qd2 Qxc6 7. Nc3 Nf6 8. Bd3 O-O 9. O-O d6 10. Qf4 Bd4 11. Bd2 a6 12. Qh4 Qc5 13. Ne2 Bxb2 14. Rab1 Qa3 15. f4 Re8 16. e5 Ng4 17. Qxh7+ Kf8 18. Rxb2 Qc5+ 19. Kh1 Nf2+ 20. Rxf2 Qxf2 21. Qh8+ Ke7 22. Qxg7 Be6 23. exd6+ Kd7 24. Qg3 Qc5 25. Rxb7 Qxd6 26. f5 Qxg3 27. fxe6+ fxe6 28. Nxg3 Rh8 29. h3 Raf8 30. Kg1 Rf7 31. Ba5 Kc6 32. Be4+ Kd6 33. Bf3 Rh4 34. Ne4+ Ke5 35. Bxc7+ Kd4 36. Rb4+ Ke3 37. Rb3+ Kd4 38. Rd3+ Kc4 1-0","Event":"Irish Championship","Site":"Dublin IRL","Date":"2008.07.12","EventDate":"2008.07.12","Round":"8","Result":"1-0","White":"Ryan Rhys Griffiths","Black":"John Loughran","ECO":"C45","WhiteElo":"?","BlackElo":"1789","PlyCount":"76","moves":["e4","e5","Nf3","Nc6","d4","exd4","Nxd4","Bc5","Nxc6","Qf6","Qd2","Qxc6","Nc3","Nf6","Bd3","O-O","O-O","d6","Qf4","Bd4","Bd2","a6","Qh4","Qc5","Ne2","Bxb2","Rab1","Qa3","f4","Re8","e5","Ng4","Qxh7+","Kf8","Rxb2","Qc5+","Kh1","Nf2+","Rxf2","Qxf2","Qh8+","Ke7","Qxg7","Be6","exd6+","Kd7","Qg3","Qc5","Rxb7","Qxd6","f5","Qxg3","fxe6+","fxe6","Nxg3","Rh8","h3","Raf8","Kg1","Rf7","Ba5","Kc6","Be4+","Kd6","Bf3","Rh4","Ne4+","Ke5","Bxc7+","Kd4","Rb4+","Ke3","Rb3+","Kd4","Rd3+","Kc4"],"fen":"8/2B2r2/p3p3/8/2k1N2r/3R1B1P/P1P3P1/6K1 w - - 7 39","Year":"2008"}