{"id":"1962319","game":"A Tang vs Macieja","result":"0-1","moveCount":26,"year":2019,"event":"PRO League Group Stage","eco":"A45 Queen's Pawn Game","pgn":"[Event \"PRO League Group Stage\"]\n[Site \"chess.com INT\"]\n[Date \"2019.03.07\"]\n[EventDate \"2019.01.08\"]\n[Round \"9\"]\n[Result \"0-1\"]\n[White \"Andrew Tang\"]\n[Black \"Bartlomiej Macieja\"]\n[ECO \"A45\"]\n[WhiteElo \"2487\"]\n[BlackElo \"2509\"]\n[PlyCount \"52\"]\n\n1. d4 Nf6 2. Bf4 d5 3. e3 c5 4. dxc5 Nc6 5. Bb5 g6 6. Nc3 Bg7 7. Nf3 O-O 8. O-O Bg4 9. h3 Bxf3 10. Qxf3 Qa5 11. a3 Nh5 12. b4 Qd8 13. Nxd5 Nxf4 14. Nxf4 Bxa1 15. Bxc6 bxc6 16. Rxa1 a5 17. Rb1 Qd2 18. Qxc6 Qxc2 19. Rf1 e6 20. Qd6 Qc3 21. Rb1 Qxa3 22. b5 Rfc8 23. Nxe6 Qa2 24. Nf4 Qxb1+ 25. Kh2 Qxb5 26. Nh5 Qb8 0-1","Event":"PRO League Group Stage","Site":"chess.com INT","Date":"2019.03.07","EventDate":"2019.01.08","Round":"9","Result":"0-1","White":"Andrew Tang","Black":"Bartlomiej Macieja","ECO":"A45","WhiteElo":"2487","BlackElo":"2509","PlyCount":"52","moves":["d4","Nf6","Bf4","d5","e3","c5","dxc5","Nc6","Bb5","g6","Nc3","Bg7","Nf3","O-O","O-O","Bg4","h3","Bxf3","Qxf3","Qa5","a3","Nh5","b4","Qd8","Nxd5","Nxf4","Nxf4","Bxa1","Bxc6","bxc6","Rxa1","a5","Rb1","Qd2","Qxc6","Qxc2","Rf1","e6","Qd6","Qc3","Rb1","Qxa3","b5","Rfc8","Nxe6","Qa2","Nf4","Qxb1+","Kh2","Qxb5","Nh5","Qb8"],"fen":"rqr3k1/5p1p/3Q2p1/p1P4N/8/4P2P/5PPK/8 w - - 2 27"}