{"id":"1206112","game":"L Toth vs A Partington","result":"½-½","moveCount":21,"year":2001,"event":"Wch U16 Girls","eco":"A80 Dutch","pgn":"[Event \"WYG16\"]\n[Site \"Oropesa del Mar ESP\"]\n[Date \"2001.10.25\"]\n[EventDate \"2001.10.06\"]\n[Round \"5\"]\n[Result \"1/2-1/2\"]\n[White \"Lili Toth\"]\n[Black \"Anna Partington\"]\n[ECO \"A80\"]\n[WhiteElo \"2139\"]\n[BlackElo \"?\"]\n[PlyCount \"42\"]\n\n1. d4 f5 2. Nc3 d5 3. Bg5 g6 4. e3 Bg7 5. Nf3 Be6 6. Ne5 Nd7 7. f4 Ngf6 8. Bd3 c6 9. O-O Ne4 10. Bxe4 dxe4 11. Ne2 Nb6 12. b3 Bxe5 13. fxe5 c5 14. Bh6 c4 15. Nf4 Qd7 16. Qe2 Rc8 17. Rfd1 Nd5 18. Nxd5 Bxd5 19. Rac1 Rg8 20. h4 a6 21. Qf2 c3 1/2-1/2","Event":"WYG16","Site":"Oropesa del Mar ESP","Date":"2001.10.25","EventDate":"2001.10.25","Round":"5","Result":"1/2-1/2","White":"Lili Toth","Black":"Anna Partington","ECO":"A80","WhiteElo":"2139","BlackElo":"?","PlyCount":"42","moves":["d4","f5","Nc3","d5","Bg5","g6","e3","Bg7","Nf3","Be6","Ne5","Nd7","f4","Ngf6","Bd3","c6","O-O","Ne4","Bxe4","dxe4","Ne2","Nb6","b3","Bxe5","fxe5","c5","Bh6","c4","Nf4","Qd7","Qe2","Rc8","Rfd1","Nd5","Nxd5","Bxd5","Rac1","Rg8","h4","a6","Qf2","c3"],"fen":"2r1k1r1/1p1qp2p/p5pB/3bPp2/3Pp2P/1Pp1P3/P1P2QP1/2RR2K1 w - - 0 22","Year":"2001"}