{"id":"2255557","game":"S Georgievski vs B Rogulj","result":"0-1","moveCount":50,"year":1979,"event":"Yugoslav Championship","eco":"D13 Queen's Gambit Declined Slav, Exchange Variation","pgn":"[Event \"Sampionat Jugoslavije 1979\"]\n[Site \"Bjelovar YUG\"]\n[Date \"1979.02.12\"]\n[EventDate \"?\"]\n[Round \"3\"]\n[Result \"0-1\"]\n[White \"Stevce Georgievski\"]\n[Black \"Branko Rogulj\"]\n[ECO \"D13\"]\n[WhiteElo \"?\"]\n[BlackElo \"?\"]\n[Source \"Perpetual Check\"]\n[PlyCount \"100\"]\n\n1. d4 Nf6 2. Nf3 c5 3. c3 cxd4 4. cxd4 d5 5. Nc3 Nc6 6. Bf4 Qb6 7. Qb3 Qxb3 8. axb3 Bf5 9. Rc1 e6 10. e3 a6 11. Be2 Na5 12. Nd2 Bb4 13. Bc7 Rc8 14. Bxa5 Bxa5 15. O-O Ke7 16. Nf3 h6 17. Na4 Ne4 18. Rfd1 Nd6 19. Nc5 Rc7 20. Bd3 Bg4 21. h3 Bxf3 22. gxf3 Rhc8 23. Bb1 f6 24. Nd3 g5 25. Rxc7+ Bxc7 26. Rc1 Nf5 27. Kf1 Nd6 28. Ke2 Nb5 29. Nc5 Bd6 30. Nd3 Rb8 31. Kf1 Na7 32. Bc2 Nc6 33. Bd1 e5 34. dxe5 fxe5 35. Ke2 Rf8 36. Ke1 e4 37. fxe4 dxe4 38. Nc5 Nb4 39. Nxe4 Nd3+ 40. Kd2 Nxc1 41. Kxc1 Bb4 42. Bg4 Rd8 43. f4 gxf4 44. exf4 Rd4 45. Ng3 Rxf4 46. Bc8 Rf3 47. Ne2 a5 48. Kc2 b6 49. Bg4 Rf2 50. Kd3 Kf6 0-1","Event":"Sampionat Jugoslavije 1979","Site":"Bjelovar YUG","Date":"1979.02.12","EventDate":"1979.02.12","Round":"3","Result":"0-1","White":"Stevce Georgievski","Black":"Branko Rogulj","ECO":"D13","WhiteElo":"?","BlackElo":"?","Source":"Perpetual Check","PlyCount":"100","moves":["d4","Nf6","Nf3","c5","c3","cxd4","cxd4","d5","Nc3","Nc6","Bf4","Qb6","Qb3","Qxb3","axb3","Bf5","Rc1","e6","e3","a6","Be2","Na5","Nd2","Bb4","Bc7","Rc8","Bxa5","Bxa5","O-O","Ke7","Nf3","h6","Na4","Ne4","Rfd1","Nd6","Nc5","Rc7","Bd3","Bg4","h3","Bxf3","gxf3","Rhc8","Bb1","f6","Nd3","g5","Rxc7+","Bxc7","Rc1","Nf5","Kf1","Nd6","Ke2","Nb5","Nc5","Bd6","Nd3","Rb8","Kf1","Na7","Bc2","Nc6","Bd1","e5","dxe5","fxe5","Ke2","Rf8","Ke1","e4","fxe4","dxe4","Nc5","Nb4","Nxe4","Nd3+","Kd2","Nxc1","Kxc1","Bb4","Bg4","Rd8","f4","gxf4","exf4","Rd4","Ng3","Rxf4","Bc8","Rf3","Ne2","a5","Kc2","b6","Bg4","Rf2","Kd3","Kf6"],"fen":"8/8/1p3k1p/p7/1b4B1/1P1K3P/1P2Nr2/8 w - - 4 51","Year":"1979"}