{"id":"2139422","game":"A Suslin vs P Ponkratov","result":"1-0","moveCount":31,"year":2003,"event":"RUS-Cup01","eco":"C55 Two Knights Defense","pgn":"[Event \"RUS-Cup01\"]\n[Site \"Tomsk\"]\n[Date \"2003.07.06\"]\n[EventDate \"?\"]\n[Round \"3\"]\n[Result \"1-0\"]\n[White \"Alexander Suslin\"]\n[Black \"Pavel Ponkratov\"]\n[ECO \"C55\"]\n[WhiteElo \"?\"]\n[BlackElo \"2296\"]\n[PlyCount \"62\"]\n\n1. e4 e5 2. Nf3 Nc6 3. Bc4 Nf6 4. d4 exd4 5. O-O Be7 6. Nxd4 d6 7. f3 O-O 8. Nc3 a5 9. Be3 Ne5 10. Be2 d5 11. exd5 Nxd5 12. Nxd5 Qxd5 13. Nf5 Qe6 14. Nxe7+ Qxe7 15. Qd4 Bf5 16. Qc3 Rfe8 17. Rfe1 Ng6 18. Bd4 Qg5 19. Bf1 Nh4 20. Bf2 c6 21. Kh1 Bg6 22. Rxe8+ Rxe8 23. Re1 Rd8 24. Be3 Qh5 25. Bb6 Ra8 26. Re5 f5 27. Bc4+ Bf7 28. Re7 Qg5 29. Bxf7+ Kf8 30. Re2 Kxf7 31. Qc4+ 1-0","Event":"RUS-Cup01","Site":"Tomsk","Date":"2003.07.06","EventDate":"2003.07.06","Round":"3","Result":"1-0","White":"Alexander Suslin","Black":"Pavel Ponkratov","ECO":"C55","WhiteElo":"?","BlackElo":"2296","PlyCount":"62","moves":["e4","e5","Nf3","Nc6","Bc4","Nf6","d4","exd4","O-O","Be7","Nxd4","d6","f3","O-O","Nc3","a5","Be3","Ne5","Be2","d5","exd5","Nxd5","Nxd5","Qxd5","Nf5","Qe6","Nxe7+","Qxe7","Qd4","Bf5","Qc3","Rfe8","Rfe1","Ng6","Bd4","Qg5","Bf1","Nh4","Bf2","c6","Kh1","Bg6","Rxe8+","Rxe8","Re1","Rd8","Be3","Qh5","Bb6","Ra8","Re5","f5","Bc4+","Bf7","Re7","Qg5","Bxf7+","Kf8","Re2","Kxf7","Qc4+"],"fen":"r7/1p3kpp/1Bp5/p4pq1/2Q4n/5P2/PPP1R1PP/7K b - - 1 31","Year":"2003"}