{"id":1007464,"Event":"Dresden","Site":"Dresden GER","Date":"1926.04.05","EventDate":"1926.04.05","Round":"2","Result":"1-0","White":"Alexander Alekhine","Black":"Max Bluemich","ECO":"A48","WhiteElo":"?","BlackElo":"?","PlyCount":"41","moves":["d4","Nf6","Nf3","g6","Bg5","Bg7","Nbd2","O-O","e3","d6","Bc4","Nc6","c3","a6","Qe2","Bg4","h3","Bd7","Nh2","Qc8","f4","e5","fxe5","dxe5","O-O","Nh5","Rxf7","Rxf7","Bxf7+","Kxf7","Qc4+","Be6","d5","Bxd5","Rf1+","Nf6","Qxd5+","Qe6","Qf3","Qf5","Bxf6"],"fen":"r7/1pp2kbp/p1n2Bp1/4pq2/8/2P1PQ1P/PP1N2PN/5RK1 b - - 0 21","Year":"1926","pgn":"[Event \"Dresden\"]\n[Site \"Dresden GER\"]\n[Date \"1926.04.05\"]\n[EventDate \"1926.04.04\"]\n[Round \"2\"]\n[Result \"1-0\"]\n[White \"Alexander Alekhine\"]\n[Black \"Max Bluemich\"]\n[ECO \"A48\"]\n[WhiteElo \"?\"]\n[BlackElo \"?\"]\n[PlyCount \"41\"]\n\n1. d4 Nf6 2. Nf3 g6 3. Bg5 Bg7 4. Nbd2 O-O 5. e3 d6 6. Bc4 Nc6 7. c3 a6 8. Qe2 Bg4 9. h3 Bd7 10. Nh2 Qc8 11. f4 e5 12. fxe5 dxe5 13. O-O Nh5 14. Rxf7 Rxf7 15. Bxf7+ Kxf7 16. Qc4+ Be6 17. d5 Bxd5 18. Rf1+ Nf6 19. Qxd5+ Qe6 20. Qf3 Qf5 21. Bxf6 1-0","result":"1-0"}