{"game":"A Hill vs J Jackson","result":"1-0","moveCount":40,"year":2015,"event":"London Chess Classic Open","eco":"A60 Benoni Defense","pgn":"[Event \"London Chess Classic Open\"]\n[Site \"London ENG\"]\n[Date \"2015.12.06\"]\n[EventDate \"2015.12.04\"]\n[Round \"4.35\"]\n[Result \"1-0\"]\n[White \"Alistair Hill\"]\n[Black \"James P Jackson\"]\n[ECO \"A60\"]\n[WhiteElo \"2157\"]\n[BlackElo \"2368\"]\n[PlyCount \"79\"]\n\n1. d4 Nf6 2. c4 c5 3. d5 e6 4. Nc3 exd5 5. cxd5 d6 6. Nf3 g6 7. Bf4 a6 8. a4 Bg7 9. h3 O-O 10. e3 Re8 11. Nd2 Nbd7 12. Be2 Ne5 13. O-O Nfd7 14. a5 f5 15. Qc2 Rb8 16. Ra3 b5 17. axb6 Qxb6 18. Rb3 Qc7 19. Ra1 Rxb3 20. Nxb3 Bb7 21. Na5 Rb8 22. Ra2 Bc8 23. Bg3 Kh8 24. e4 fxe4 25. Nxe4 Nb6 26. Nc6 Nxd5 27. Nxb8 Nb4 28. Qa4 h6 29. Nxa6 Bxa6 30. Bxa6 d5 31. Nc3 d4 32. Qe8+ Kh7 33. Bc4 h5 34. Nd5 Nxd5 35. Bxd5 Qd6 36. Bg8+ Kh6 37. h4 g5 38. Ra7 Qg6 39. Qxg6+ Kxg6 40. Rxg7+ 1-0","Event":"London Chess Classic Open","Site":"London ENG","Date":"2015.12.06","EventDate":"2015.12.04","Round":"4.35","Result":"1-0","White":"Alistair Hill","Black":"James P Jackson","ECO":"A60","WhiteElo":"2157","BlackElo":"2368","PlyCount":"79","moves":["d4","Nf6","c4","c5","d5","e6","Nc3","exd5","cxd5","d6","Nf3","g6","Bf4","a6","a4","Bg7","h3","O-O","e3","Re8","Nd2","Nbd7","Be2","Ne5","O-O","Nfd7","a5","f5","Qc2","Rb8","Ra3","b5","axb6","Qxb6","Rb3","Qc7","Ra1","Rxb3","Nxb3","Bb7","Na5","Rb8","Ra2","Bc8","Bg3","Kh8","e4","fxe4","Nxe4","Nb6","Nc6","Nxd5","Nxb8","Nb4","Qa4","h6","Nxa6","Bxa6","Bxa6","d5","Nc3","d4","Qe8+","Kh7","Bc4","h5","Nd5","Nxd5","Bxd5","Qd6","Bg8+","Kh6","h4","g5","Ra7","Qg6","Qxg6+","Kxg6","Rxg7+"],"fen":"6B1/6R1/6k1/2p1n1pp/3p3P/6B1/1P3PP1/6K1 b - - 0 40","id":"1810674"}