{"id":"2450095","game":"Y Ranola vs M Paragua","result":"1-0","moveCount":30,"year":2011,"event":"Philippine Championship","eco":"A07 King's Indian Attack","pgn":"[Event \"ch-PHI\"]\n[Site \"Manila PHI\"]\n[Date \"2011.07.22\"]\n[EventDate \"?\"]\n[Round \"12\"]\n[Result \"1-0\"]\n[White \"Yves Ranola\"]\n[Black \"Mark Paragua\"]\n[ECO \"A07\"]\n[WhiteElo \"2377\"]\n[BlackElo \"2545\"]\n[PlyCount \"60\"]\n\n1. Nf3 d5 2. g3 Nf6 3. Bg2 c6 4. O-O Bf5 5. d3 e6 6. Nbd2 h6 7. Qe1 Be7 8. e4 Bh7 9. Qe2 O-O 10. Ne5 Nbd7 11. Nxd7 Nxd7 12. f4 a5 13. a4 Nc5 14. Kh1 Re8 15. g4 Qb6 16. b3 Na6 17. Bb2 Nb4 18. Nf3 Qa6 19. Rae1 dxe4 20. dxe4 Qxe2 21. Rxe2 b5 22. f5 Bc5 23. Ne5 exf5 24. gxf5 f6 25. Nd7 Ba7 26. axb5 cxb5 27. e5 Rac8 28. Be4 fxe5 29. f6 Bxe4+ 30. Rxe4 1-0","Event":"ch-PHI","Site":"Manila PHI","Date":"2011.07.22","EventDate":"?","Round":"12","Result":"1-0","White":"Yves Ranola","Black":"Mark Paragua","ECO":"A07","WhiteElo":"2377","BlackElo":"2545","PlyCount":"60","moves":["Nf3","d5","g3","Nf6","Bg2","c6","O-O","Bf5","d3","e6","Nbd2","h6","Qe1","Be7","e4","Bh7","Qe2","O-O","Ne5","Nbd7","Nxd7","Nxd7","f4","a5","a4","Nc5","Kh1","Re8","g4","Qb6","b3","Na6","Bb2","Nb4","Nf3","Qa6","Rae1","dxe4","dxe4","Qxe2","Rxe2","b5","f5","Bc5","Ne5","exf5","gxf5","f6","Nd7","Ba7","axb5","cxb5","e5","Rac8","Be4","fxe5","f6","Bxe4+","Rxe4"],"fen":"2r1r1k1/b2N2p1/5P1p/pp2p3/1n2R3/1P6/1BP4P/5R1K b - - 0 30"}