{"id":"1083158","game":"K Hulak vs Korchnoi","result":"0-1","moveCount":44,"year":1987,"event":"Hoogovens","eco":"E39 Nimzo-Indian, Classical, Pirc Variation","pgn":"[Event \"Hoogovens\"]\n[Site \"Wijk aan Zee NED\"]\n[Date \"1987.01.21\"]\n[EventDate \"?\"]\n[Round \"5\"]\n[Result \"0-1\"]\n[White \"Krunoslav Hulak\"]\n[Black \"Viktor Korchnoi\"]\n[ECO \"E39\"]\n[WhiteElo \"2540\"]\n[BlackElo \"2625\"]\n[PlyCount \"88\"]\n\n1. d4 Nf6 2. c4 e6 3. Nc3 Bb4 4. Qc2 c5 5. dxc5 O-O 6. Be3 Qe7 7. Nf3 Na6 8. a3 Bxc3+ 9. Qxc3 Nxc5 10. Bd4 b6 11. e3 Bb7 12. Be2 Rfc8 13. O-O d5 14. Bxf6 Qxf6 15. Qxf6 gxf6 16. cxd5 Bxd5 17. Rad1 Nb3 18. Bd3 Rc7 19. h3 Kg7 20. Rfe1 Bxf3 21. gxf3 Rd8 22. Kg2 Rcd7 23. Bc2 Nd2 24. Rc1 f5 25. Bd1 Kf6 26. Be2 f4 27. Rc3 Rd5 28. Kh2 Rf5 29. Rd1 fxe3 30. Rxe3 Rfd5 31. Rc1 Rg8 32. h4 b5 33. b3 a5 34. Kh3 b4 35. a4 Re5 36. Rxe5 Kxe5 37. Rc5+ Kd4 38. Rxa5 Nxb3 39. Ra7 Nc1 40. Bd1 Nd3 41. Rxf7 Nxf2+ 42. Kh2 Nxd1 43. Rd7+ Kc3 44. Rxd1 b3 0-1","Event":"Hoogovens","Site":"Wijk aan Zee NED","Date":"1987.01.21","EventDate":"1987.01.21","Round":"5","Result":"0-1","White":"Krunoslav Hulak","Black":"Viktor Korchnoi","ECO":"E39","WhiteElo":"2540","BlackElo":"2625","PlyCount":"88","moves":["d4","Nf6","c4","e6","Nc3","Bb4","Qc2","c5","dxc5","O-O","Be3","Qe7","Nf3","Na6","a3","Bxc3+","Qxc3","Nxc5","Bd4","b6","e3","Bb7","Be2","Rfc8","O-O","d5","Bxf6","Qxf6","Qxf6","gxf6","cxd5","Bxd5","Rad1","Nb3","Bd3","Rc7","h3","Kg7","Rfe1","Bxf3","gxf3","Rd8","Kg2","Rcd7","Bc2","Nd2","Rc1","f5","Bd1","Kf6","Be2","f4","Rc3","Rd5","Kh2","Rf5","Rd1","fxe3","Rxe3","Rfd5","Rc1","Rg8","h4","b5","b3","a5","Kh3","b4","a4","Re5","Rxe5","Kxe5","Rc5+","Kd4","Rxa5","Nxb3","Ra7","Nc1","Bd1","Nd3","Rxf7","Nxf2+","Kh2","Nxd1","Rd7+","Kc3","Rxd1","b3"],"fen":"6r1/7p/4p3/8/P6P/1pk2P2/7K/3R4 w - - 0 45","Year":"1987"}