{"id":"1447066","game":"J Marcinkiewicz vs G Cardelli","result":"½-½","moveCount":41,"year":2001,"event":"W-ch20 q01 corr","eco":"B33 Sicilian","pgn":"[Event \"W-ch20 q01 corr\"]\n[Site \"ICCF Email\"]\n[Date \"2001.07.02\"]\n[EventDate \"2001.07.02\"]\n[Round \"?\"]\n[Result \"1/2-1/2\"]\n[White \"Jan Stanislav Marcinkiewicz\"]\n[Black \"Gabriele Cardelli\"]\n[ECO \"B33\"]\n[WhiteElo \"?\"]\n[BlackElo \"?\"]\n[PlyCount \"81\"]\n\n1. e4 c5 2. Nf3 Nc6 3. d4 cxd4 4. Nxd4 Nf6 5. Nc3 e5 6. Ndb5 d6 7. Bg5 a6 8. Na3 b5 9. Bxf6 gxf6 10. Nd5 Bg7 11. c3 f5 12. exf5 Bxf5 13. Nc2 O-O 14. Nce3 Bd7 15. Bd3 f5 16. Qh5 e4 17. Bc2 Kh8 18. O-O Ne5 19. Rad1 Ra7 20. f3 exf3 21. gxf3 Nc4 22. Nxc4 bxc4 23. Kh1 Rb7 24. b3 Be5 25. Rb1 Be8 26. Qh3 Qc8 27. Rfd1 cxb3 28. axb3 Bc6 29. c4 Rg7 30. Bd3 Qe6 31. Rg1 a5 32. Rxg7 Bxg7 33. Be4 Bd7 34. Bd3 Rb8 35. Qh4 Bc6 36. Qh3 Bd7 37. Qh4 Re8 38. Rg1 Qf7 39. Re1 Be5 40. f4 Be6 41. fxe5 1/2-1/2","Event":"W-ch20 q01 corr","Site":"ICCF Email","Date":"2001.07.02","EventDate":"2001.07.02","Round":"?","Result":"1/2-1/2","White":"Jan Stanislav Marcinkiewicz","Black":"Gabriele Cardelli","ECO":"B33","WhiteElo":"?","BlackElo":"?","PlyCount":"81","moves":["e4","c5","Nf3","Nc6","d4","cxd4","Nxd4","Nf6","Nc3","e5","Ndb5","d6","Bg5","a6","Na3","b5","Bxf6","gxf6","Nd5","Bg7","c3","f5","exf5","Bxf5","Nc2","O-O","Nce3","Bd7","Bd3","f5","Qh5","e4","Bc2","Kh8","O-O","Ne5","Rad1","Ra7","f3","exf3","gxf3","Nc4","Nxc4","bxc4","Kh1","Rb7","b3","Be5","Rb1","Be8","Qh3","Qc8","Rfd1","cxb3","axb3","Bc6","c4","Rg7","Bd3","Qe6","Rg1","a5","Rxg7","Bxg7","Be4","Bd7","Bd3","Rb8","Qh4","Bc6","Qh3","Bd7","Qh4","Re8","Rg1","Qf7","Re1","Be5","f4","Be6","fxe5"],"fen":"4r2k/5q1p/3pb3/p2NPp2/2P4Q/1P1B4/7P/4R2K b - - 0 41","Year":"2001"}