{"id":"1429384","game":"Hertneck vs A Greenfeld","result":"0-1","moveCount":30,"year":1987,"event":"Munich Zonal","eco":"A07 King's Indian Attack","pgn":"[Event \"Munich Zonal\"]\n[Site \"Munich FRG\"]\n[Date \"1987.01.??\"]\n[EventDate \"?\"]\n[Round \"?\"]\n[Result \"0-1\"]\n[White \"Gerald Hertneck\"]\n[Black \"Alon Greenfeld\"]\n[ECO \"A07\"]\n[WhiteElo \"?\"]\n[BlackElo \"?\"]\n[PlyCount \"60\"]\n\n1.e4 c5 2.Nc3 Nc6 3.g3 g6 4.Bg2 Bg7 5.d3 d6 6.Nge2 e5 7.Nd5 Nge7 8.c4 O-O 9.O-O Rb8 10.Nec3 Nxd5 11.exd5 Nd4 12.a4 h5 13.Rb1 Bg4 14.f3 Bf5 15.Be3 h4 16.Rf2 a5 17.Bf1 Bd7 18.Ne4 f5 19.Bg5 Qb6 20.Nc3 hxg3 21.hxg3 Kf7 22.b3 Rh8 23.Bd2 Rh5 24.Ne2 Rbh8 25.Bg2 Nxe2+ 26.Qxe2 Qd8 27.Re1 f4 28.g4 Rh2 29.Qe4 Qh4 30.Kf1 Qg3 0-1","Event":"Munich Zonal","Site":"Munich FRG","Date":"1987.01.??","EventDate":"1987.01.??","Round":"?","Result":"0-1","White":"Gerald Hertneck","Black":"Alon Greenfeld","ECO":"A07","WhiteElo":"?","BlackElo":"?","PlyCount":"60","moves":["e4","c5","Nc3","Nc6","g3","g6","Bg2","Bg7","d3","d6","Nge2","e5","Nd5","Nge7","c4","O-O","O-O","Rb8","Nec3","Nxd5","exd5","Nd4","a4","h5","Rb1","Bg4","f3","Bf5","Be3","h4","Rf2","a5","Bf1","Bd7","Ne4","f5","Bg5","Qb6","Nc3","hxg3","hxg3","Kf7","b3","Rh8","Bd2","Rh5","Ne2","Rbh8","Bg2","Nxe2+","Qxe2","Qd8","Re1","f4","g4","Rh2","Qe4","Qh4","Kf1","Qg3"],"fen":"7r/1p1b1kb1/3p2p1/p1pPp3/P1P1QpP1/1P1P1Pq1/3B1RBr/4RK2 w - - 5 31","Year":"1987"}