{"id":"2525836","game":"E Jelling vs M Trepp","result":"0-1","moveCount":23,"year":1980,"event":"International Junior Tournament","eco":"B20 Sicilian","pgn":"[Event \"DEN-ch jr\"]\n[Site \"Vordingborg DEN\"]\n[Date \"1980.06.??\"]\n[EventDate \"?\"]\n[Round \"?\"]\n[Result \"0-1\"]\n[White \"Erik Jelling\"]\n[Black \"Markus Trepp\"]\n[ECO \"B20\"]\n[WhiteElo \"?\"]\n[BlackElo \"?\"]\n[PlyCount \"46\"]\n\n1. e4 c5 2. b3 Nc6 3. Bb2 e5 4. Nc3 d6 5. g3 Nge7 6. Bg2 g6 7. Nge2 Bg7 8. O-O O-O 9. f4 Nd4 10. Nxd4 cxd4 11. Ne2 Bg4 12. d3 Qd7 13. c4 dxc3 14. Bxc3 Qc6 15. Bb2 Qb6+ 16. Kh1 Qe3 17. Re1 Qf2 18. h3 exf4 19. hxg4 f3 20. Bf1 Bxb2 21. Rb1 Be5 22. d4 fxe2 23. Rxe2 Qxd4 0-1","Event":"DEN-ch jr","Site":"Vordingborg DEN","Date":"1980.06.??","EventDate":"1980.06.??","Round":"?","Result":"0-1","White":"Erik Jelling","Black":"Markus Trepp","ECO":"B20","WhiteElo":"?","BlackElo":"?","PlyCount":"46","moves":["e4","c5","b3","Nc6","Bb2","e5","Nc3","d6","g3","Nge7","Bg2","g6","Nge2","Bg7","O-O","O-O","f4","Nd4","Nxd4","cxd4","Ne2","Bg4","d3","Qd7","c4","dxc3","Bxc3","Qc6","Bb2","Qb6+","Kh1","Qe3","Re1","Qf2","h3","exf4","hxg4","f3","Bf1","Bxb2","Rb1","Be5","d4","fxe2","Rxe2","Qxd4"],"fen":"r4rk1/pp2np1p/3p2p1/4b3/3qP1P1/1P4P1/P3R3/1R1Q1B1K w - - 0 24","Year":"1980"}