{"id":"1694516","game":"Grischuk vs Pelletier","result":"1-0","moveCount":46,"year":2012,"event":"European Club Cup","eco":"C02 French, Advance","pgn":"[Event \"European Club Cup\"]\n[Site \"Eilat ISR\"]\n[Date \"2012.10.14\"]\n[EventDate \"2012.10.11\"]\n[Round \"4\"]\n[Result \"1-0\"]\n[White \"Alexander Grischuk\"]\n[Black \"Yannick Pelletier\"]\n[ECO \"C02\"]\n[WhiteElo \"2752\"]\n[BlackElo \"2601\"]\n[PlyCount \"91\"]\n\n1. e4 e6 2. d4 d5 3. e5 c5 4. c3 Qb6 5. Nf3 Nc6 6. a3 Nh6 7. b4 cxd4 8. Bxh6 gxh6 9. cxd4 Bd7 10. Ra2 Rc8 11. Be2 Bg7 12. O-O O-O 13. b5 Na5 14. a4 Rc7 15. Na3 Rfc8 16. Nc2 Nb3 17. Ne3 Rc3 18. Bd3 Rxd3 19. Qxd3 Nc1 20. Qb1 Nxa2 21. Qxa2 h5 22. Qa3 a6 23. Rb1 Be8 24. g4 f6 25. Qe7 fxe5 26. Nxe5 Kh8 27. Rd1 axb5 28. a5 Qd8 29. Qxe6 hxg4 30. Nf5 Rc7 31. Re1 Bh5 32. Ng3 Be8 33. Nf5 Bh5 34. Nd6 Qf8 35. Qxd5 b4 36. Nxb7 Rc2 37. Rf1 Qg8 38. Qd7 b3 39. Nd6 Bxe5 40. dxe5 b2 41. Qb7 Qa2 42. Nf5 Qf7 43. a6 Bg6 44. e6 Qc7 45. e7 h5 46. Qb5 1-0","Event":"European Club Cup","Site":"Eilat ISR","Date":"2012.10.14","EventDate":"2012.10.14","Round":"4","Result":"1-0","White":"Alexander Grischuk","Black":"Yannick Pelletier","ECO":"C02","WhiteElo":"2752","BlackElo":"2601","PlyCount":"91","moves":["e4","e6","d4","d5","e5","c5","c3","Qb6","Nf3","Nc6","a3","Nh6","b4","cxd4","Bxh6","gxh6","cxd4","Bd7","Ra2","Rc8","Be2","Bg7","O-O","O-O","b5","Na5","a4","Rc7","Na3","Rfc8","Nc2","Nb3","Ne3","Rc3","Bd3","Rxd3","Qxd3","Nc1","Qb1","Nxa2","Qxa2","h5","Qa3","a6","Rb1","Be8","g4","f6","Qe7","fxe5","Nxe5","Kh8","Rd1","axb5","a5","Qd8","Qxe6","hxg4","Nf5","Rc7","Re1","Bh5","Ng3","Be8","Nf5","Bh5","Nd6","Qf8","Qxd5","b4","Nxb7","Rc2","Rf1","Qg8","Qd7","b3","Nd6","Bxe5","dxe5","b2","Qb7","Qa2","Nf5","Qf7","a6","Bg6","e6","Qc7","e7","h5","Qb5"],"fen":"7k/2q1P3/P5b1/1Q3N1p/6p1/8/1pr2P1P/5RK1 b - - 1 46","Year":"2012"}