{"id":"1454893","game":"V Sergeev vs Y Kruppa","result":"0-1","moveCount":73,"year":2007,"event":"5th Platonov Memorial","eco":"A40 Queen's Pawn Game","pgn":"[Event \"5th Platonov Memorial\"]\n[Site \"Kiev UKR\"]\n[Date \"2007.02.10\"]\n[EventDate \"2007.02.03\"]\n[Round \"9\"]\n[Result \"0-1\"]\n[White \"Vladimir Sergeev\"]\n[Black \"Yuri Kruppa\"]\n[ECO \"A40\"]\n[WhiteElo \"2452\"]\n[BlackElo \"2531\"]\n[PlyCount \"146\"]\n\n1. d4 e6 2. Nf3 c5 3. c3 Nc6 4. Bg5 f6 5. Bf4 Qb6 6. Qd2 cxd4 7. cxd4 g5 8. Be3 d5 9. Nc3 Bd7 10. h4 g4 11. Nh2 h5 12. Na4 Qb4 13. Nc3 Rc8 14. g3 Na5 15. Qc2 Ne7 16. Bg2 Nf5 17. Bc1 Nxd4 18. Qg6+ Ke7 19. O-O Rxc3 20. bxc3 Qxc3 21. Qb1 Nxe2+ 22. Kh1 Nxc1 23. Rxc1 Qa3 24. Nf1 Bh6 25. Qg6 Nc6 26. Re1 Ne5 27. Qc2 Bc6 28. Rab1 Kf7 29. Nd2 Qd3 30. Rb2 Qxc2 31. Rxc2 Nd3 32. Re2 e5 33. Nb3 Ke6 34. Nd4+ Kd7 35. Nxc6 bxc6 36. Rc3 e4 37. Ra3 Ra8 38. Bf1 Bf8 39. Rxd3 exd3 40. Rd2 Bb4 41. Rxd3 Kd6 42. Rb3 a5 43. a3 Bc5 44. a4 Bxf2 45. Kg2 Bd4 46. Bd3 Re8 47. Bg6 Re5 48. Rb7 c5 49. Rb6+ Ke7 50. Rb7+ Kd6 51. Rb6+ Kd7 52. Rxf6 Re2+ 53. Kf1 Re3 54. Ra6 Rxg3 55. Rxa5 Rh3 56. Bxh5 Rxh4 57. Bf7 Kd6 58. Ra6+ Ke5 59. Re6+ Kf4 60. Re8 Rh1+ 61. Ke2 Rh2+ 62. Kd3 Rh3+ 63. Kd2 Rh2+ 64. Kd3 Be3 65. Rf8 Rd2+ 66. Kc3 d4+ 67. Kb3 g3 68. a5 g2 69. Bd5+ Ke5 70. Bxg2 Rxg2 71. a6 Rg7 72. Ra8 Kd5 73. a7 Rd7 0-1","Event":"5th Platonov Memorial","Site":"Kiev UKR","Date":"2007.02.10","EventDate":"2007.02.10","Round":"9","Result":"0-1","White":"Vladimir Sergeev","Black":"Yuri Kruppa","ECO":"A40","WhiteElo":"2452","BlackElo":"2531","PlyCount":"146","moves":["d4","e6","Nf3","c5","c3","Nc6","Bg5","f6","Bf4","Qb6","Qd2","cxd4","cxd4","g5","Be3","d5","Nc3","Bd7","h4","g4","Nh2","h5","Na4","Qb4","Nc3","Rc8","g3","Na5","Qc2","Ne7","Bg2","Nf5","Bc1","Nxd4","Qg6+","Ke7","O-O","Rxc3","bxc3","Qxc3","Qb1","Nxe2+","Kh1","Nxc1","Rxc1","Qa3","Nf1","Bh6","Qg6","Nc6","Re1","Ne5","Qc2","Bc6","Rab1","Kf7","Nd2","Qd3","Rb2","Qxc2","Rxc2","Nd3","Re2","e5","Nb3","Ke6","Nd4+","Kd7","Nxc6","bxc6","Rc3","e4","Ra3","Ra8","Bf1","Bf8","Rxd3","exd3","Rd2","Bb4","Rxd3","Kd6","Rb3","a5","a3","Bc5","a4","Bxf2","Kg2","Bd4","Bd3","Re8","Bg6","Re5","Rb7","c5","Rb6+","Ke7","Rb7+","Kd6","Rb6+","Kd7","Rxf6","Re2+","Kf1","Re3","Ra6","Rxg3","Rxa5","Rh3","Bxh5","Rxh4","Bf7","Kd6","Ra6+","Ke5","Re6+","Kf4","Re8","Rh1+","Ke2","Rh2+","Kd3","Rh3+","Kd2","Rh2+","Kd3","Be3","Rf8","Rd2+","Kc3","d4+","Kb3","g3","a5","g2","Bd5+","Ke5","Bxg2","Rxg2","a6","Rg7","Ra8","Kd5","a7","Rd7"],"fen":"R7/P2r4/8/2pk4/3p4/1K2b3/8/8 w - - 1 74","Year":"2007"}