{"id":"1864223","game":"I Kadimova vs A Stefanova","result":"0-1","moveCount":28,"year":2006,"event":"EU-ch (Women) 7th playoff","eco":"D11 Queen's Gambit Declined Slav","pgn":"[Event \"EU-ch (Women) 7th playoff\"]\n[Site \"Kusadasi TUR\"]\n[Date \"2006.??.??\"]\n[EventDate \"?\"]\n[Round \"1.2\"]\n[Result \"0-1\"]\n[White \"Ilaha Akif q覺z覺 Kadimova\"]\n[Black \"Antoaneta Stefanova\"]\n[ECO \"D11\"]\n[WhiteElo \"2310\"]\n[BlackElo \"2502\"]\n[PlyCount \"55\"]\n\n1.d4 d5 2.c4 c6 3.Nf3 Nf6 4.Qb3 e6 5.g3 b6 6.Bg2 Nbd7 7.O-O Ba6 8.cxd5 cxd5 9.Nc3 Be7 10.Bf4 Bc4 11.Qa4 O-O 12.Rfc1 a5 13.Nd2 Rc8 14.e4 Bb4 15.a3 b5 16.Qd1 Bxc3 17.Rxc3 dxe4 18.Nxe4 Nxe4 19.Bxe4 Nf6 20.Bb7 Nd5 21.Rf3 Nxf4 22.Bxc8 Be2 23.Qd2 Nh3+ 24.Kg2 Bxf3+ 25.Kxf3 Qd5+ 26.Ke3 Rxc8 27.f4 f5 28.Qd1 0-1","Event":"EU-ch (Women) 7th playoff","Site":"Kusadasi TUR","Date":"2006.??.??","EventDate":"2006.??.??","Round":"1.2","Result":"0-1","White":"Ilaha Akif q覺z覺 Kadimova","Black":"Antoaneta Stefanova","ECO":"D11","WhiteElo":"2310","BlackElo":"2502","PlyCount":"55","moves":["d4","d5","c4","c6","Nf3","Nf6","Qb3","e6","g3","b6","Bg2","Nbd7","O-O","Ba6","cxd5","cxd5","Nc3","Be7","Bf4","Bc4","Qa4","O-O","Rfc1","a5","Nd2","Rc8","e4","Bb4","a3","b5","Qd1","Bxc3","Rxc3","dxe4","Nxe4","Nxe4","Bxe4","Nf6","Bb7","Nd5","Rf3","Nxf4","Bxc8","Be2","Qd2","Nh3+","Kg2","Bxf3+","Kxf3","Qd5+","Ke3","Rxc8","f4","f5","Qd1"],"fen":"2r3k1/6pp/4p3/pp1q1p2/3P1P2/P3K1Pn/1P5P/R2Q4 b - - 1 28","Year":"2006"}