{"id":"2130579","game":"E Handoko vs S Guliev","result":"0-1","moveCount":29,"year":2007,"event":"Dubai op 9th","eco":"C50 Giuoco Piano","pgn":"[Event \"Dubai op 9th\"]\n[Site \"Dubai\"]\n[Date \"2007.04.28\"]\n[EventDate \"?\"]\n[Round \"7\"]\n[Result \"0-1\"]\n[White \"Edhi Handoko\"]\n[Black \"Sarhan Guliev\"]\n[ECO \"C50\"]\n[WhiteElo \"2441\"]\n[BlackElo \"2486\"]\n[PlyCount \"58\"]\n\n1. e4 e5 2. Nf3 Nc6 3. Bc4 Nf6 4. d3 Bc5 5. O-O d6 6. c3 Qe7 7. h3 h6 8. b4 Bb6 9. a4 a6 10. Be3 Bxe3 11. fxe3 O-O 12. Ra2 Be6 13. Qb3 Bxc4 14. Qxc4 Qd7 15. Nh2 d5 16. exd5 Nxd5 17. b5 Na5 18. Qe4 f5 19. Qxe5 Rae8 20. Qd4 c5 21. Qxc5 Nxe3 22. Re1 Nb3 23. Qa3 Nc4 24. Rxe8 Nxa3 25. Rxf8+ Kxf8 26. Nxa3 Qxd3 27. Nf1 Qxc3 28. Rc2 Qd4+ 29. Kh1 Qa1 0-1","Event":"Dubai op 9th","Site":"Dubai","Date":"2007.04.28","EventDate":"2007.04.28","Round":"7","Result":"0-1","White":"Edhi Handoko","Black":"Sarhan Guliev","ECO":"C50","WhiteElo":"2441","BlackElo":"2486","PlyCount":"58","moves":["e4","e5","Nf3","Nc6","Bc4","Nf6","d3","Bc5","O-O","d6","c3","Qe7","h3","h6","b4","Bb6","a4","a6","Be3","Bxe3","fxe3","O-O","Ra2","Be6","Qb3","Bxc4","Qxc4","Qd7","Nh2","d5","exd5","Nxd5","b5","Na5","Qe4","f5","Qxe5","Rae8","Qd4","c5","Qxc5","Nxe3","Re1","Nb3","Qa3","Nc4","Rxe8","Nxa3","Rxf8+","Kxf8","Nxa3","Qxd3","Nf1","Qxc3","Rc2","Qd4+","Kh1","Qa1"],"fen":"5k2/1p4p1/p6p/1P3p2/P7/Nn5P/2R3P1/q4N1K w - - 4 30","Year":"2007"}