{"id":"1193759","game":"S Stajner vs L Gonda","result":"0-1","moveCount":19,"year":2001,"event":"EU-ch U14","eco":"B42 Sicilian, Kan","pgn":"[Event \"EYCC B14\"]\n[Site \"Chalkidiki GRE\"]\n[Date \"2001.09.04\"]\n[EventDate \"2001.08.31\"]\n[Round \"5\"]\n[Result \"0-1\"]\n[White \"Samo Stajner\"]\n[Black \"Laszlo Gonda\"]\n[ECO \"B42\"]\n[WhiteElo \"2113\"]\n[BlackElo \"2307\"]\n[PlyCount \"38\"]\n\n1. e4 c5 2. Nf3 e6 3. d4 cxd4 4. Nxd4 a6 5. Bd3 g6 6. c4 Bg7 7. Be3 d5 8. cxd5 exd5 9. O-O Ne7 10. Nc3 O-O 11. Qd2 dxe4 12. Bxe4 f5 13. Bc2 f4 14. Bb3+ Kh8 15. Ne4 fxe3 16. fxe3 Nf5 17. Qb4 Nxd4 18. Rxf8+ Qxf8 19. Nd6 Nbc6 0-1","Event":"EYCC B14","Site":"Chalkidiki GRE","Date":"2001.09.04","EventDate":"2001.08.31","Round":"5","Result":"0-1","White":"Samo Stajner","Black":"Laszlo Gonda","ECO":"B42","WhiteElo":"2113","BlackElo":"2307","PlyCount":"38","moves":["e4","c5","Nf3","e6","d4","cxd4","Nxd4","a6","Bd3","g6","c4","Bg7","Be3","d5","cxd5","exd5","O-O","Ne7","Nc3","O-O","Qd2","dxe4","Bxe4","f5","Bc2","f4","Bb3+","Kh8","Ne4","fxe3","fxe3","Nf5","Qb4","Nxd4","Rxf8+","Qxf8","Nd6","Nbc6"],"fen":"r1b2q1k/1p4bp/p1nN2p1/8/1Q1n4/1B2P3/PP4PP/R5K1 w - - 2 20"}