{"id":"1486484","game":"V Lukov vs Vachier-Lagrave","result":"1-0","moveCount":33,"year":2000,"event":"Noisy le Grand op","eco":"A14 English","pgn":"[Event \"Noisy le Grand op\"]\n[Site \"Noisy le Grand\"]\n[Date \"2000.??.??\"]\n[EventDate \"2000.??.??\"]\n[Round \"6\"]\n[Result \"1-0\"]\n[White \"Valentin Lukov\"]\n[Black \"Maxime Vachier-Lagrave\"]\n[ECO \"A14\"]\n[WhiteElo \"2469\"]\n[BlackElo \"2637\"]\n[PlyCount \"65\"]\n\n1. Nf3 d5 2. c4 e6 3. g3 Nf6 4. Bg2 Be7 5. O-O O-O 6. d4 c5 7. cxd5 Nxd5 8. Nc3 Nb6 9. dxc5 Bxc5 10. Qc2 Nc6 11. Rd1 Qc7 12. Ne4 Be7 13. Bf4 e5 14. Bxe5 Qxe5 15. Nxe5 Nxe5 16. Qc7 Nc6 17. Rac1 Bd8 18. Qf4 f5 19. Nc5 Bf6 20. b3 h6 21. Bxc6 bxc6 22. Qc7 Re8 23. Qxc6 Rxe2 24. Na4 Rxa2 25. Qxa8 Nxa8 26. Rxc8+ Kh7 27. Rxa8 Be7 28. Rd7 Bf6 29. Raxa7 Ra1+ 30. Kg2 Rb1 31. Nc5 Kg6 32. h4 f4 33. g4 1-0","Event":"Noisy le Grand op","Site":"Noisy le Grand","Date":"2000.??.??","EventDate":"2000.??.??","Round":"6","Result":"1-0","White":"Valentin Lukov","Black":"Maxime Vachier-Lagrave","ECO":"A14","WhiteElo":"2469","BlackElo":"2637","PlyCount":"65","moves":["Nf3","d5","c4","e6","g3","Nf6","Bg2","Be7","O-O","O-O","d4","c5","cxd5","Nxd5","Nc3","Nb6","dxc5","Bxc5","Qc2","Nc6","Rd1","Qc7","Ne4","Be7","Bf4","e5","Bxe5","Qxe5","Nxe5","Nxe5","Qc7","Nc6","Rac1","Bd8","Qf4","f5","Nc5","Bf6","b3","h6","Bxc6","bxc6","Qc7","Re8","Qxc6","Rxe2","Na4","Rxa2","Qxa8","Nxa8","Rxc8+","Kh7","Rxa8","Be7","Rd7","Bf6","Raxa7","Ra1+","Kg2","Rb1","Nc5","Kg6","h4","f4","g4"],"fen":"8/R2R2p1/5bkp/2N5/5pPP/1P6/5PK1/1r6 b - - 0 33","Year":"2000"}