{"id":"1854721","game":"Korneev vs A Fier","result":"½-½","moveCount":26,"year":2016,"event":"1st Paytakht Cup","eco":"B33 Sicilian","pgn":"[Event \"1st Paytakht Cup\"]\n[Site \"Tehran IRI\"]\n[Date \"2016.10.29\"]\n[EventDate \"2016.10.25\"]\n[Round \"6.2\"]\n[Result \"1/2-1/2\"]\n[White \"Oleg Korneev\"]\n[Black \"Alexandr Hilario Takeda dos Santos Fier\"]\n[ECO \"B33\"]\n[WhiteElo \"2581\"]\n[BlackElo \"2614\"]\n[PlyCount \"52\"]\n\n1. e4 c5 2. Nf3 e6 3. d4 cxd4 4. Nxd4 Nf6 5. Nc3 Nc6 6. Ndb5 d6 7. Bf4 e5 8. Bg5 a6 9. Na3 b5 10. Nd5 Be7 11. Bxf6 Bxf6 12. c3 Bg5 13. Nc2 Ne7 14. a4 bxa4 15. Ncb4 O-O 16. Qxa4 a5 17. Nxe7+ Qxe7 18. Nd5 Qb7 19. Bb5 Rb8 20. c4 Be6 21. Rd1 f5 22. exf5 Rxf5 23. O-O Qa7 24. b4 Rbf8 25. Qxa5 Qf7 26. Qa2 Bxd5 1/2-1/2","Event":"1st Paytakht Cup","Site":"Tehran IRI","Date":"2016.10.29","EventDate":"2016.10.29","Round":"6.2","Result":"1/2-1/2","White":"Oleg Korneev","Black":"Alexandr Hilario Takeda dos Santos Fier","ECO":"B33","WhiteElo":"2581","BlackElo":"2614","PlyCount":"52","moves":["e4","c5","Nf3","e6","d4","cxd4","Nxd4","Nf6","Nc3","Nc6","Ndb5","d6","Bf4","e5","Bg5","a6","Na3","b5","Nd5","Be7","Bxf6","Bxf6","c3","Bg5","Nc2","Ne7","a4","bxa4","Ncb4","O-O","Qxa4","a5","Nxe7+","Qxe7","Nd5","Qb7","Bb5","Rb8","c4","Be6","Rd1","f5","exf5","Rxf5","O-O","Qa7","b4","Rbf8","Qxa5","Qf7","Qa2","Bxd5"],"fen":"5rk1/5qpp/3p4/1B1bprb1/1PP5/8/Q4PPP/3R1RK1 w - - 0 27","Year":"2016"}