{"id":"1544187","game":"H Tikkanen vs C Hoi","result":"1-0","moveCount":46,"year":2009,"event":"Scandinavian Open","eco":"A54 Old Indian, Ukrainian Variation, 4.Nf3","pgn":"[Event \"Scandinavian Open\"]\n[Site \"Copenhagen\"]\n[Date \"2009.04.19\"]\n[EventDate \"2009.??.??\"]\n[Round \"2\"]\n[Result \"1-0\"]\n[White \"Hans Tikkanen\"]\n[Black \"Carsten Hoi\"]\n[ECO \"A54\"]\n[WhiteElo \"2425\"]\n[BlackElo \"2387\"]\n[PlyCount \"91\"]\n\n1. d4 Nf6 2. c4 d6 3. Nc3 e5 4. Nf3 Nc6 5. d5 Ne7 6. e4 Ng6 7. h4 Bg4 8. Qa4+ Bd7 9. Qb3 b6 10. g3 Be7 11. Be2 h6 12. Nh2 O-O 13. h5 Nh8 14. Be3 Qc8 15. O-O-O a6 16. f4 Rb8 17. fxe5 dxe5 18. g4 Bc5 19. Bxc5 bxc5 20. Qa3 Qb7 21. Rhg1 Nh7 22. Nf3 f6 23. Ne1 Nf7 24. Nd3 Bc8 25. Nxc5 Qb6 26. Nb3 Nhg5 27. c5 Qb4 28. Qxb4 Rxb4 29. Nd2 Nh3 30. Rg3 Nf4 31. Bc4 Ng5 32. a3 Rb8 33. Nb3 Kh7 34. Na5 g6 35. hxg6+ Kxg6 36. Nc6 Ra8 37. Ne7+ Kg7 38. Nf5+ Bxf5 39. exf5 Rfd8 40. b4 h5 41. gxh5 Kh6 42. Kb2 Nfh3 43. Rd2 Nf4 44. Kb3 e4 45. Rf2 Nxh5 46. Rh2 1-0","Event":"Scandinavian Open","Site":"Copenhagen","Date":"2009.04.19","EventDate":"2009.04.19","Round":"2","Result":"1-0","White":"Hans Tikkanen","Black":"Carsten Hoi","ECO":"A54","WhiteElo":"2425","BlackElo":"2387","PlyCount":"91","moves":["d4","Nf6","c4","d6","Nc3","e5","Nf3","Nc6","d5","Ne7","e4","Ng6","h4","Bg4","Qa4+","Bd7","Qb3","b6","g3","Be7","Be2","h6","Nh2","O-O","h5","Nh8","Be3","Qc8","O-O-O","a6","f4","Rb8","fxe5","dxe5","g4","Bc5","Bxc5","bxc5","Qa3","Qb7","Rhg1","Nh7","Nf3","f6","Ne1","Nf7","Nd3","Bc8","Nxc5","Qb6","Nb3","Nhg5","c5","Qb4","Qxb4","Rxb4","Nd2","Nh3","Rg3","Nf4","Bc4","Ng5","a3","Rb8","Nb3","Kh7","Na5","g6","hxg6+","Kxg6","Nc6","Ra8","Ne7+","Kg7","Nf5+","Bxf5","exf5","Rfd8","b4","h5","gxh5","Kh6","Kb2","Nfh3","Rd2","Nf4","Kb3","e4","Rf2","Nxh5","Rh2"],"fen":"r2r4/2p5/p4p1k/2PP1Pnn/1PB1p3/PKN3R1/7R/8 b - - 1 46","Year":"2009"}