{"id":"2261762","game":"P Greicius vs E Papadiamandis","result":"½-½","moveCount":19,"year":2022,"event":"European Individual Championship","eco":"D85 Grunfeld","pgn":"[Event \"European Individual Championship\"]\n[Site \"Terme Catez SLO\"]\n[Date \"2022.03.31\"]\n[EventDate \"2022.03.27\"]\n[Round \"5.11\"]\n[Result \"1/2-1/2\"]\n[White \"Pijus Greicius\"]\n[Black \"Elliot Papadiamandis\"]\n[ECO \"D85\"]\n[WhiteElo \"2100\"]\n[BlackElo \"2406\"]\n[Source \"Lichess\"]\n[PlyCount \"38\"]\n\n1. d4 Nf6 2. c4 g6 3. Nc3 d5 4. cxd5 Nxd5 5. e4 Nxc3 6. bxc3 Bg7 7. Nf3 c5 8. h3 O-O 9. Be2 Nc6 10. Be3 cxd4 11. cxd4 Qa5+ 12. Bd2 Qa3 13. d5 Ne5 14. O-O Bd7 15. Rb1 Ba4 16. Qe1 Qxa2 17. Rxb7 Rfb8 18. Rxb8+ Rxb8 19. Bf4 Qb2 1/2-1/2","Event":"European Individual Championship","Site":"Terme Catez SLO","Date":"2022.03.31","EventDate":"2022.03.27","Round":"5.11","Result":"1/2-1/2","White":"Pijus Greicius","Black":"Elliot Papadiamandis","ECO":"D85","WhiteElo":"2100","BlackElo":"2406","Source":"Lichess","PlyCount":"38","moves":["d4","Nf6","c4","g6","Nc3","d5","cxd5","Nxd5","e4","Nxc3","bxc3","Bg7","Nf3","c5","h3","O-O","Be2","Nc6","Be3","cxd4","cxd4","Qa5+","Bd2","Qa3","d5","Ne5","O-O","Bd7","Rb1","Ba4","Qe1","Qxa2","Rxb7","Rfb8","Rxb8+","Rxb8","Bf4","Qb2"],"fen":"1r4k1/p3ppbp/6p1/3Pn3/b3PB2/5N1P/1q2BPP1/4QRK1 w - - 2 20"}