{"id":"1882884","game":"N Georgiadis vs Morozevich","result":"½-½","moveCount":42,"year":2017,"event":"Biel","eco":"C93 Ruy Lopez, Closed, Smyslov Defense","pgn":"[Event \"Biel\"]\n[Site \"Biel SUI\"]\n[Date \"2017.07.30\"]\n[EventDate \"2017.07.23\"]\n[Round \"6\"]\n[Result \"1/2-1/2\"]\n[White \"Nico Georgiadis\"]\n[Black \"Alexander Morozevich\"]\n[ECO \"C93\"]\n[WhiteElo \"2496\"]\n[BlackElo \"2675\"]\n[PlyCount \"83\"]\n\n1. e4 e5 2. Nf3 Nc6 3. Bb5 a6 4. Ba4 Nf6 5. O-O Be7 6. Re1 b5 7. Bb3 d6 8. c3 O-O 9. h3 Re8 10. d4 Bb7 11. Nbd2 Bf8 12. a3 h6 13. Bc2 d5 14. dxe5 Nxe5 15. Nxe5 Rxe5 16. Nf3 Re8 17. e5 Ne4 18. Bf4 c5 19. Qe2 f6 20. Rad1 fxe5 21. Bxe5 Qb6 22. Qe3 Re6 23. Bb3 Nd6 24. Bxd5 Bxd5 25. Rxd5 Nc4 26. Qc1 Qc6 27. Red1 Rae8 28. Bg3 Re2 29. b3 Nb2 30. Ne5 R8xe5 31. Rxe5 Rxe5 32. Bxe5 Nxd1 33. Qxd1 Qe6 34. Bf4 Be7 35. Be3 c4 36. b4 Bf6 37. Qd2 Qe4 38. Kf1 Qb1+ 39. Ke2 Qb3 40. Bd4 Bxd4 41. Qxd4 Qxa3 42. Qd5+ 1/2-1/2","Event":"Biel","Site":"Biel SUI","Date":"2017.07.30","EventDate":"2017.07.30","Round":"6","Result":"1/2-1/2","White":"Nico Georgiadis","Black":"Alexander Morozevich","ECO":"C93","WhiteElo":"2496","BlackElo":"2675","PlyCount":"83","moves":["e4","e5","Nf3","Nc6","Bb5","a6","Ba4","Nf6","O-O","Be7","Re1","b5","Bb3","d6","c3","O-O","h3","Re8","d4","Bb7","Nbd2","Bf8","a3","h6","Bc2","d5","dxe5","Nxe5","Nxe5","Rxe5","Nf3","Re8","e5","Ne4","Bf4","c5","Qe2","f6","Rad1","fxe5","Bxe5","Qb6","Qe3","Re6","Bb3","Nd6","Bxd5","Bxd5","Rxd5","Nc4","Qc1","Qc6","Red1","Rae8","Bg3","Re2","b3","Nb2","Ne5","R8xe5","Rxe5","Rxe5","Bxe5","Nxd1","Qxd1","Qe6","Bf4","Be7","Be3","c4","b4","Bf6","Qd2","Qe4","Kf1","Qb1+","Ke2","Qb3","Bd4","Bxd4","Qxd4","Qxa3","Qd5+"],"fen":"6k1/6p1/p6p/1p1Q4/1Pp5/q1P4P/4KPP1/8 b - - 1 42","Year":"2017"}