{"id":"2369533","game":"A Matanovic vs R Maric","result":"½-½","moveCount":14,"year":1965,"event":"Yugoslav Championship 1966","eco":"C10 French","pgn":"[Event \"Sampionat Jugoslavije 1966\"]\n[Site \"Titograd YUG\"]\n[Date \"1965.11.25\"]\n[EventDate \"1965.11.24\"]\n[Round \"2\"]\n[Result \"1/2-1/2\"]\n[White \"Aleksandar Matanovic\"]\n[Black \"Rudolf Maric\"]\n[ECO \"C10\"]\n[WhiteElo \"?\"]\n[BlackElo \"?\"]\n[Source \"Perpetual Check\"]\n[PlyCount \"28\"]\n\n1. e4 e6 2. d4 d5 3. Nd2 dxe4 4. Nxe4 Qd5 5. Bd3 Nf6 6. Nxf6+ gxf6 7. Nf3 Rg8 8. O-O Nc6 9. Re1 Bd6 10. g3 Qh5 11. Be2 Qh3 12. Bf1 Qh5 13. Be2 Qh3 14. Bf1 Qh5 1/2-1/2","Event":"Sampionat Jugoslavije 1966","Site":"Titograd YUG","Date":"1965.11.25","EventDate":"1965.11.24","Round":"2","Result":"1/2-1/2","White":"Aleksandar Matanovic","Black":"Rudolf Maric","ECO":"C10","WhiteElo":"?","BlackElo":"?","Source":"Perpetual Check","PlyCount":"28","moves":["e4","e6","d4","d5","Nd2","dxe4","Nxe4","Qd5","Bd3","Nf6","Nxf6+","gxf6","Nf3","Rg8","O-O","Nc6","Re1","Bd6","g3","Qh5","Be2","Qh3","Bf1","Qh5","Be2","Qh3","Bf1","Qh5"],"fen":"r1b1k1r1/ppp2p1p/2nbpp2/7q/3P4/5NP1/PPP2P1P/R1BQRBK1 w q - 9 15"}