{"id":"1755073","game":"R Cifuentes Parada vs H Grooten","result":"1-0","moveCount":25,"year":1993,"event":"Hoogovens Open","eco":"A30 English, Symmetrical","pgn":"[Event \"Hoogovens Open\"]\n[Site \"Wijk aan Zee NED\"]\n[Date \"1993.01.19\"]\n[EventDate \"1993.01.14\"]\n[Round \"2\"]\n[Result \"1-0\"]\n[White \"Roberto Cifuentes Parada\"]\n[Black \"Herman Grooten\"]\n[ECO \"A30\"]\n[WhiteElo \"2480\"]\n[BlackElo \"2410\"]\n[PlyCount \"49\"]\n\n1.c4 c5 2.Nf3 Nf6 3.Nc3 b6 4.g3 Bb7 5.Bg2 g6 6.O-O Bg7 7.Re1 d6 8.e4 Nbd7 9.d4 cxd4 10.Nxd4 Rc8 11.e5 dxe5 12.Bxb7 exd4 13.Bxc8 dxc3 14.Bxd7+ Nxd7 15.Rb1 O-O 16.bxc3 Qc8 17.Rxe7 Rd8 18.Bf4 Bf6 19.Re3 g5 20.Bd6 Qxc4 21.Be7 Bxe7 22.Rxe7 Qc6 23.Qd4 Kf8 24.Rbe1 f6 25.Rxh7 1-0","Event":"Hoogovens Open","Site":"Wijk aan Zee NED","Date":"1993.01.19","EventDate":"1993.01.19","Round":"2","Result":"1-0","White":"Roberto Cifuentes Parada","Black":"Herman Grooten","ECO":"A30","WhiteElo":"2480","BlackElo":"2410","PlyCount":"49","moves":["c4","c5","Nf3","Nf6","Nc3","b6","g3","Bb7","Bg2","g6","O-O","Bg7","Re1","d6","e4","Nbd7","d4","cxd4","Nxd4","Rc8","e5","dxe5","Bxb7","exd4","Bxc8","dxc3","Bxd7+","Nxd7","Rb1","O-O","bxc3","Qc8","Rxe7","Rd8","Bf4","Bf6","Re3","g5","Bd6","Qxc4","Be7","Bxe7","Rxe7","Qc6","Qd4","Kf8","Rbe1","f6","Rxh7"],"fen":"3r1k2/p2n3R/1pq2p2/6p1/3Q4/2P3P1/P4P1P/4R1K1 b - - 0 25","Year":"1993"}