{"id":"2338066","game":"C Henriquez Villagra vs B Nguku Namale","result":"1-0","moveCount":30,"year":2022,"event":"Chennai Olympiad","eco":"B12 Caro-Kann Defense","pgn":"[Event \"44th Olympiad\"]\n[Site \"Chennai IND\"]\n[Date \"2022.07.29\"]\n[EventDate \"?\"]\n[Round \"1.17\"]\n[Result \"1-0\"]\n[White \"Henriquez Villagra Cristobal\"]\n[Black \"Namale Ben Nguku\"]\n[ECO \"B12\"]\n[WhiteElo \"2620\"]\n[BlackElo \"1962\"]\n[PlyCount \"60\"]\n\n1. e4 c6 2. d4 d5 3. f3 dxe4 4. fxe4 Qb6 5. Nf3 Nf6 6. e5 Ng8 7. Nbd2 Bf5 8. Nc4 Qc7 9. Bd3 Bxd3 10. Qxd3 e6 11. O-O h6 12. Bf4 Nd7 13. Bg3 b5 14. Ne3 Nb6 15. a4 Nxa4 16. b3 Nb6 17. Nd2 Ne7 18. c4 Qd7 19. Ne4 Nec8 20. Bh4 bxc4 21. bxc4 Be7 22. Bxe7 Qxe7 23. c5 Nd7 24. Rf4 O-O 25. Ng4 h5 26. Ngf6+ Nxf6 27. Nxf6+ gxf6 28. Qg3+ Kh7 29. Rh4 Kh6 30. Qg4 1-0","Event":"44th Olympiad","Site":"Chennai IND","Date":"2022.07.29","EventDate":"2022.07.29","Round":"1.17","Result":"1-0","White":"Henriquez Villagra Cristobal","Black":"Namale Ben Nguku","ECO":"B12","WhiteElo":"2620","BlackElo":"1962","PlyCount":"60","moves":["e4","c6","d4","d5","f3","dxe4","fxe4","Qb6","Nf3","Nf6","e5","Ng8","Nbd2","Bf5","Nc4","Qc7","Bd3","Bxd3","Qxd3","e6","O-O","h6","Bf4","Nd7","Bg3","b5","Ne3","Nb6","a4","Nxa4","b3","Nb6","Nd2","Ne7","c4","Qd7","Ne4","Nec8","Bh4","bxc4","bxc4","Be7","Bxe7","Qxe7","c5","Nd7","Rf4","O-O","Ng4","h5","Ngf6+","Nxf6","Nxf6+","gxf6","Qg3+","Kh7","Rh4","Kh6","Qg4"],"fen":"r1n2r2/p3qp2/2p1pp1k/2P1P2p/3P2QR/8/6PP/R5K1 b - - 5 30","Year":"2022"}