{"id":"1277544","game":"A Vouldis vs R Schmaltz","result":"1-0","moveCount":48,"year":2003,"event":"Athens Acropolis GM","eco":"B42 Sicilian, Kan","pgn":"[Event \"Athens Acropolis GM\"]\n[Site \"Athens GRE\"]\n[Date \"2003.08.30\"]\n[EventDate \"2003.??.??\"]\n[Round \"6\"]\n[Result \"1-0\"]\n[White \"Angelos Vouldis\"]\n[Black \"Roland Schmaltz\"]\n[ECO \"B42\"]\n[WhiteElo \"2539\"]\n[BlackElo \"2530\"]\n[PlyCount \"95\"]\n\n1.e4 c5 2.Nf3 e6 3.d4 cxd4 4.Nxd4 a6 5.Bd3 Qb6 6.c3 d6 7.O-O Nf6 8.Be3 Qc7 9.c4 g6 10.Nc3 Bg7 11.Rc1 Nbd7 12.f3 O-O 13.Qd2 Re8 14.Rfd1 b6 15.Bf1 Bb7 16.Qf2 Bf8 17.b4 Rab8 18.Nb3 Ba8 19.Na4 Bc6 20.b5 Ba8 21.bxa6 Nc5 22.Nbxc5 bxc5 23.Nc3 Rb6 24.Nb5 Qe7 25.a7 Rc8 26.Qh4 Ne8 27.Qxe7 Bxe7 28.Rb1 Ra6 29.Rd2 f6 30.g4 Kf7 31.Bf2 g5 32.h4 h6 33.Bg3 e5 34.Rh2 Ng7 35.Rd1 Kg6 36. Rhd2 Rcc6 37.hxg5 hxg5 38.Bf2 Ne6 39.Be3 Rcb6 40.Kf2 Nd4 41.Kg3 Bc6 42. Bxd4 cxd4 43.Rh2 Ra4 44.Bd3 Rba6 45.Rdh1 Bf8 46.Rh7 Rxa2 47.Nxd4 R2a3 48. Ne6 1-0","Event":"Athens Acropolis GM","Site":"Athens GRE","Date":"2003.08.30","EventDate":"2003.08.30","Round":"6","Result":"1-0","White":"Angelos Vouldis","Black":"Roland Schmaltz","ECO":"B42","WhiteElo":"2539","BlackElo":"2530","PlyCount":"95","moves":["e4","c5","Nf3","e6","d4","cxd4","Nxd4","a6","Bd3","Qb6","c3","d6","O-O","Nf6","Be3","Qc7","c4","g6","Nc3","Bg7","Rc1","Nbd7","f3","O-O","Qd2","Re8","Rfd1","b6","Bf1","Bb7","Qf2","Bf8","b4","Rab8","Nb3","Ba8","Na4","Bc6","b5","Ba8","bxa6","Nc5","Nbxc5","bxc5","Nc3","Rb6","Nb5","Qe7","a7","Rc8","Qh4","Ne8","Qxe7","Bxe7","Rb1","Ra6","Rd2","f6","g4","Kf7","Bf2","g5","h4","h6","Bg3","e5","Rh2","Ng7","Rd1","Kg6","Rhd2","Rcc6","hxg5","hxg5","Bf2","Ne6","Be3","Rcb6","Kf2","Nd4","Kg3","Bc6","Bxd4","cxd4","Rh2","Ra4","Bd3","Rba6","Rdh1","Bf8","Rh7","Rxa2","Nxd4","R2a3","Ne6"],"fen":"5b2/P6R/r1bpNpk1/4p1p1/2P1P1P1/r2B1PK1/8/7R b - - 2 48","Year":"2003"}